Raspbot_Lib/Raspbot_Lib.py
Raspbot_Lib/__init__.py
Raspbot_Lib-0.0.2.1.dist-info/METADATA
Raspbot_Lib-0.0.2.1.dist-info/WHEEL
Raspbot_Lib-0.0.2.1.dist-info/top_level.txt
Raspbot_Lib-0.0.2.1.dist-info/RECORD
