Metadata-Version: 2.1
Name: Raspbot-Lib
Version: 0.0.2.1
Summary: Raspbot drvier V0.0.2
Home-page: https://category.yahboom.net/
Author: Yahboom Team
License: UNKNOWN
Platform: UNKNOWN
